asciigen/__init__.py
asciigen/colorscales.py
asciigen/image.py
asciigen/main.py
asciigen/render.py
asciigen/renderer.py
asciigen-0.1.1.dist-info/entry_points.txt
asciigen-0.1.1.dist-info/WHEEL
asciigen-0.1.1.dist-info/METADATA
asciigen-0.1.1.dist-info/RECORD
