Metadata-Version: 2.1
Name: asciigen
Version: 0.1.1
Summary: Ascii art image generator
Author: Juan Lara
Author-email: julara@unal.edu.co
Requires-Python: >=3.8
Classifier: Programming Language :: Python :: 3
Classifier: Programming Language :: Python :: 3.10
Classifier: Programming Language :: Python :: 3.8
Classifier: Programming Language :: Python :: 3.9
Requires-Dist: numpy (>=1.22.3,<2.0.0)
Requires-Dist: opencv-python (>=4.5.5,<5.0.0)
Requires-Dist: urwid (>=2.1.2,<3.0.0)
